{
  "type": "File",
  "start": 0,
  "end": 413,
  "loc": {
    "start": {
      "line": 1,
      "column": 0
    },
    "end": {
      "line": 18,
      "column": 0
    }
  },
  "program": {
    "type": "Program",
    "start": 0,
    "end": 413,
    "loc": {
      "start": {
        "line": 1,
        "column": 0
      },
      "end": {
        "line": 18,
        "column": 0
      }
    },
    "sourceType": "module",
    "body": [
      {
        "type": "ImportDeclaration",
        "start": 0,
        "end": 41,
        "loc": {
          "start": {
            "line": 1,
            "column": 0
          },
          "end": {
            "line": 1,
            "column": 41
          }
        },
        "specifiers": [
          {
            "type": "ImportDefaultSpecifier",
            "start": 7,
            "end": 18,
            "loc": {
              "start": {
                "line": 1,
                "column": 7
              },
              "end": {
                "line": 1,
                "column": 18
              }
            },
            "local": {
              "type": "Identifier",
              "start": 7,
              "end": 18,
              "loc": {
                "start": {
                  "line": 1,
                  "column": 7
                },
                "end": {
                  "line": 1,
                  "column": 18
                },
                "identifierName": "_NamedTuple"
              },
              "name": "_NamedTuple"
            }
          }
        ],
        "source": {
          "type": "StringLiteral",
          "start": 24,
          "end": 39,
          "loc": {
            "start": {
              "line": 1,
              "column": 24
            },
            "end": {
              "line": 1,
              "column": 39
            }
          },
          "extra": {
            "rawValue": "./_NamedTuple",
            "raw": "'./_NamedTuple'"
          },
          "value": "./_NamedTuple"
        }
      },
      {
        "type": "ImportDeclaration",
        "start": 42,
        "end": 83,
        "loc": {
          "start": {
            "line": 2,
            "column": 0
          },
          "end": {
            "line": 2,
            "column": 41
          }
        },
        "specifiers": [
          {
            "type": "ImportDefaultSpecifier",
            "start": 49,
            "end": 60,
            "loc": {
              "start": {
                "line": 2,
                "column": 7
              },
              "end": {
                "line": 2,
                "column": 18
              }
            },
            "local": {
              "type": "Identifier",
              "start": 49,
              "end": 60,
              "loc": {
                "start": {
                  "line": 2,
                  "column": 7
                },
                "end": {
                  "line": 2,
                  "column": 18
                },
                "identifierName": "_namedtuple"
              },
              "name": "_namedtuple"
            }
          }
        ],
        "source": {
          "type": "StringLiteral",
          "start": 66,
          "end": 81,
          "loc": {
            "start": {
              "line": 2,
              "column": 24
            },
            "end": {
              "line": 2,
              "column": 39
            }
          },
          "extra": {
            "rawValue": "./_namedtuple",
            "raw": "'./_namedtuple'"
          },
          "value": "./_namedtuple"
        }
      },
      {
        "type": "ImportDeclaration",
        "start": 85,
        "end": 139,
        "loc": {
          "start": {
            "line": 4,
            "column": 0
          },
          "end": {
            "line": 4,
            "column": 54
          }
        },
        "specifiers": [
          {
            "type": "ImportSpecifier",
            "start": 94,
            "end": 98,
            "loc": {
              "start": {
                "line": 4,
                "column": 9
              },
              "end": {
                "line": 4,
                "column": 13
              }
            },
            "imported": {
              "type": "Identifier",
              "start": 94,
              "end": 98,
              "loc": {
                "start": {
                  "line": 4,
                  "column": 9
                },
                "end": {
                  "line": 4,
                  "column": 13
                },
                "identifierName": "Dict"
              },
              "name": "Dict"
            },
            "local": {
              "type": "Identifier",
              "start": 94,
              "end": 98,
              "loc": {
                "start": {
                  "line": 4,
                  "column": 9
                },
                "end": {
                  "line": 4,
                  "column": 13
                },
                "identifierName": "Dict"
              },
              "name": "Dict"
            }
          }
        ],
        "source": {
          "type": "StringLiteral",
          "start": 106,
          "end": 137,
          "loc": {
            "start": {
              "line": 4,
              "column": 21
            },
            "end": {
              "line": 4,
              "column": 52
            }
          },
          "extra": {
            "rawValue": "@aureooms/js-collections-dict",
            "raw": "'@aureooms/js-collections-dict'"
          },
          "value": "@aureooms/js-collections-dict"
        }
      },
      {
        "type": "ImportDeclaration",
        "start": 140,
        "end": 208,
        "loc": {
          "start": {
            "line": 5,
            "column": 0
          },
          "end": {
            "line": 5,
            "column": 68
          }
        },
        "specifiers": [
          {
            "type": "ImportSpecifier",
            "start": 149,
            "end": 160,
            "loc": {
              "start": {
                "line": 5,
                "column": 9
              },
              "end": {
                "line": 5,
                "column": 20
              }
            },
            "imported": {
              "type": "Identifier",
              "start": 149,
              "end": 160,
              "loc": {
                "start": {
                  "line": 5,
                  "column": 9
                },
                "end": {
                  "line": 5,
                  "column": 20
                },
                "identifierName": "OrderedDict"
              },
              "name": "OrderedDict"
            },
            "local": {
              "type": "Identifier",
              "start": 149,
              "end": 160,
              "loc": {
                "start": {
                  "line": 5,
                  "column": 9
                },
                "end": {
                  "line": 5,
                  "column": 20
                },
                "identifierName": "OrderedDict"
              },
              "name": "OrderedDict"
            }
          }
        ],
        "source": {
          "type": "StringLiteral",
          "start": 168,
          "end": 206,
          "loc": {
            "start": {
              "line": 5,
              "column": 28
            },
            "end": {
              "line": 5,
              "column": 66
            }
          },
          "extra": {
            "rawValue": "@aureooms/js-collections-ordereddict",
            "raw": "'@aureooms/js-collections-ordereddict'"
          },
          "value": "@aureooms/js-collections-ordereddict"
        }
      },
      {
        "type": "Identifier",
        "start": 210,
        "end": 264,
        "loc": {
          "start": {
            "line": 7,
            "column": 0
          },
          "end": {
            "line": 7,
            "column": 54
          }
        },
        "declarations": [
          {
            "type": "VariableDeclarator",
            "start": 216,
            "end": 262,
            "loc": {
              "start": {
                "line": 7,
                "column": 6
              },
              "end": {
                "line": 7,
                "column": 52
              }
            },
            "id": {
              "type": "Identifier",
              "start": 216,
              "end": 226,
              "loc": {
                "start": {
                  "line": 7,
                  "column": 6
                },
                "end": {
                  "line": 7,
                  "column": 16
                },
                "identifierName": "NamedTuple"
              },
              "name": "NamedTuple"
            },
            "init": {
              "type": "CallExpression",
              "start": 229,
              "end": 262,
              "loc": {
                "start": {
                  "line": 7,
                  "column": 19
                },
                "end": {
                  "line": 7,
                  "column": 52
                }
              },
              "callee": {
                "type": "Identifier",
                "start": 229,
                "end": 240,
                "loc": {
                  "start": {
                    "line": 7,
                    "column": 19
                  },
                  "end": {
                    "line": 7,
                    "column": 30
                  },
                  "identifierName": "_NamedTuple"
                },
                "name": "_NamedTuple"
              },
              "arguments": [
                {
                  "type": "Identifier",
                  "start": 242,
                  "end": 246,
                  "loc": {
                    "start": {
                      "line": 7,
                      "column": 32
                    },
                    "end": {
                      "line": 7,
                      "column": 36
                    },
                    "identifierName": "Dict"
                  },
                  "name": "Dict"
                },
                {
                  "type": "Identifier",
                  "start": 249,
                  "end": 260,
                  "loc": {
                    "start": {
                      "line": 7,
                      "column": 39
                    },
                    "end": {
                      "line": 7,
                      "column": 50
                    },
                    "identifierName": "OrderedDict"
                  },
                  "name": "OrderedDict"
                }
              ]
            }
          }
        ],
        "kind": "const",
        "name": "_",
        "leadingComments": [],
        "trailingComments": []
      },
      {
        "type": "Identifier",
        "start": 265,
        "end": 311,
        "loc": {
          "start": {
            "line": 8,
            "column": 0
          },
          "end": {
            "line": 8,
            "column": 46
          }
        },
        "declarations": [
          {
            "type": "VariableDeclarator",
            "start": 271,
            "end": 309,
            "loc": {
              "start": {
                "line": 8,
                "column": 6
              },
              "end": {
                "line": 8,
                "column": 44
              }
            },
            "id": {
              "type": "Identifier",
              "start": 271,
              "end": 281,
              "loc": {
                "start": {
                  "line": 8,
                  "column": 6
                },
                "end": {
                  "line": 8,
                  "column": 16
                },
                "identifierName": "namedtuple"
              },
              "name": "namedtuple"
            },
            "init": {
              "type": "CallExpression",
              "start": 284,
              "end": 309,
              "loc": {
                "start": {
                  "line": 8,
                  "column": 19
                },
                "end": {
                  "line": 8,
                  "column": 44
                }
              },
              "callee": {
                "type": "Identifier",
                "start": 284,
                "end": 295,
                "loc": {
                  "start": {
                    "line": 8,
                    "column": 19
                  },
                  "end": {
                    "line": 8,
                    "column": 30
                  },
                  "identifierName": "_namedtuple"
                },
                "name": "_namedtuple"
              },
              "arguments": [
                {
                  "type": "Identifier",
                  "start": 297,
                  "end": 307,
                  "loc": {
                    "start": {
                      "line": 8,
                      "column": 32
                    },
                    "end": {
                      "line": 8,
                      "column": 42
                    },
                    "identifierName": "NamedTuple"
                  },
                  "name": "NamedTuple"
                }
              ]
            }
          }
        ],
        "kind": "const",
        "name": "_",
        "leadingComments": [],
        "trailingComments": []
      },
      {
        "type": "Identifier",
        "start": 313,
        "end": 340,
        "loc": {
          "start": {
            "line": 10,
            "column": 0
          },
          "end": {
            "line": 10,
            "column": 27
          }
        },
        "declaration": {
          "type": "Identifier",
          "start": 328,
          "end": 338,
          "loc": {
            "start": {
              "line": 10,
              "column": 15
            },
            "end": {
              "line": 10,
              "column": 25
            },
            "identifierName": "namedtuple"
          },
          "name": "namedtuple"
        },
        "name": "_",
        "leadingComments": [],
        "trailingComments": []
      },
      {
        "type": "ExportNamedDeclaration",
        "start": 342,
        "end": 412,
        "loc": {
          "start": {
            "line": 12,
            "column": 0
          },
          "end": {
            "line": 17,
            "column": 3
          }
        },
        "declaration": null,
        "specifiers": [
          {
            "type": "ExportSpecifier",
            "start": 352,
            "end": 362,
            "loc": {
              "start": {
                "line": 13,
                "column": 1
              },
              "end": {
                "line": 13,
                "column": 11
              }
            },
            "local": {
              "type": "Identifier",
              "start": 352,
              "end": 362,
              "loc": {
                "start": {
                  "line": 13,
                  "column": 1
                },
                "end": {
                  "line": 13,
                  "column": 11
                },
                "identifierName": "namedtuple"
              },
              "name": "namedtuple"
            },
            "exported": {
              "type": "Identifier",
              "start": 352,
              "end": 362,
              "loc": {
                "start": {
                  "line": 13,
                  "column": 1
                },
                "end": {
                  "line": 13,
                  "column": 11
                },
                "identifierName": "namedtuple"
              },
              "name": "namedtuple"
            }
          },
          {
            "type": "ExportSpecifier",
            "start": 366,
            "end": 376,
            "loc": {
              "start": {
                "line": 14,
                "column": 1
              },
              "end": {
                "line": 14,
                "column": 11
              }
            },
            "local": {
              "type": "Identifier",
              "start": 366,
              "end": 376,
              "loc": {
                "start": {
                  "line": 14,
                  "column": 1
                },
                "end": {
                  "line": 14,
                  "column": 11
                },
                "identifierName": "NamedTuple"
              },
              "name": "NamedTuple"
            },
            "exported": {
              "type": "Identifier",
              "start": 366,
              "end": 376,
              "loc": {
                "start": {
                  "line": 14,
                  "column": 1
                },
                "end": {
                  "line": 14,
                  "column": 11
                },
                "identifierName": "NamedTuple"
              },
              "name": "NamedTuple"
            }
          },
          {
            "type": "ExportSpecifier",
            "start": 380,
            "end": 391,
            "loc": {
              "start": {
                "line": 15,
                "column": 1
              },
              "end": {
                "line": 15,
                "column": 12
              }
            },
            "local": {
              "type": "Identifier",
              "start": 380,
              "end": 391,
              "loc": {
                "start": {
                  "line": 15,
                  "column": 1
                },
                "end": {
                  "line": 15,
                  "column": 12
                },
                "identifierName": "_namedtuple"
              },
              "name": "_namedtuple"
            },
            "exported": {
              "type": "Identifier",
              "start": 380,
              "end": 391,
              "loc": {
                "start": {
                  "line": 15,
                  "column": 1
                },
                "end": {
                  "line": 15,
                  "column": 12
                },
                "identifierName": "_namedtuple"
              },
              "name": "_namedtuple"
            }
          },
          {
            "type": "ExportSpecifier",
            "start": 395,
            "end": 406,
            "loc": {
              "start": {
                "line": 16,
                "column": 1
              },
              "end": {
                "line": 16,
                "column": 12
              }
            },
            "local": {
              "type": "Identifier",
              "start": 395,
              "end": 406,
              "loc": {
                "start": {
                  "line": 16,
                  "column": 1
                },
                "end": {
                  "line": 16,
                  "column": 12
                },
                "identifierName": "_NamedTuple"
              },
              "name": "_NamedTuple"
            },
            "exported": {
              "type": "Identifier",
              "start": 395,
              "end": 406,
              "loc": {
                "start": {
                  "line": 16,
                  "column": 1
                },
                "end": {
                  "line": 16,
                  "column": 12
                },
                "identifierName": "_NamedTuple"
              },
              "name": "_NamedTuple"
            }
          }
        ],
        "source": null
      },
      {
        "type": "ExportDefaultDeclaration",
        "start": 313,
        "end": 340,
        "loc": {
          "start": {
            "line": 10,
            "column": 0
          },
          "end": {
            "line": 10,
            "column": 27
          }
        },
        "declaration": {
          "type": "VariableDeclaration",
          "start": 265,
          "end": 311,
          "loc": {
            "start": {
              "line": 8,
              "column": 0
            },
            "end": {
              "line": 8,
              "column": 46
            }
          },
          "declarations": [
            {
              "type": "VariableDeclarator",
              "start": 271,
              "end": 309,
              "loc": {
                "start": {
                  "line": 8,
                  "column": 6
                },
                "end": {
                  "line": 8,
                  "column": 44
                }
              },
              "id": {
                "type": "Identifier",
                "start": 271,
                "end": 281,
                "loc": {
                  "start": {
                    "line": 8,
                    "column": 6
                  },
                  "end": {
                    "line": 8,
                    "column": 16
                  },
                  "identifierName": "namedtuple"
                },
                "name": "namedtuple"
              },
              "init": {
                "type": "CallExpression",
                "start": 284,
                "end": 309,
                "loc": {
                  "start": {
                    "line": 8,
                    "column": 19
                  },
                  "end": {
                    "line": 8,
                    "column": 44
                  }
                },
                "callee": {
                  "type": "Identifier",
                  "start": 284,
                  "end": 295,
                  "loc": {
                    "start": {
                      "line": 8,
                      "column": 19
                    },
                    "end": {
                      "line": 8,
                      "column": 30
                    },
                    "identifierName": "_namedtuple"
                  },
                  "name": "_namedtuple"
                },
                "arguments": [
                  {
                    "type": "Identifier",
                    "start": 297,
                    "end": 307,
                    "loc": {
                      "start": {
                        "line": 8,
                        "column": 32
                      },
                      "end": {
                        "line": 8,
                        "column": 42
                      },
                      "identifierName": "NamedTuple"
                    },
                    "name": "NamedTuple"
                  }
                ]
              }
            }
          ],
          "kind": "const",
          "leadingComments": [],
          "trailingComments": []
        }
      },
      {
        "type": "ExportNamedDeclaration",
        "start": 342,
        "end": 412,
        "loc": {
          "start": {
            "line": 12,
            "column": 0
          },
          "end": {
            "line": 17,
            "column": 3
          }
        },
        "declaration": {
          "type": "VariableDeclaration",
          "start": 210,
          "end": 264,
          "loc": {
            "start": {
              "line": 7,
              "column": 0
            },
            "end": {
              "line": 7,
              "column": 54
            }
          },
          "declarations": [
            {
              "type": "VariableDeclarator",
              "start": 216,
              "end": 262,
              "loc": {
                "start": {
                  "line": 7,
                  "column": 6
                },
                "end": {
                  "line": 7,
                  "column": 52
                }
              },
              "id": {
                "type": "Identifier",
                "start": 216,
                "end": 226,
                "loc": {
                  "start": {
                    "line": 7,
                    "column": 6
                  },
                  "end": {
                    "line": 7,
                    "column": 16
                  },
                  "identifierName": "NamedTuple"
                },
                "name": "NamedTuple"
              },
              "init": {
                "type": "CallExpression",
                "start": 229,
                "end": 262,
                "loc": {
                  "start": {
                    "line": 7,
                    "column": 19
                  },
                  "end": {
                    "line": 7,
                    "column": 52
                  }
                },
                "callee": {
                  "type": "Identifier",
                  "start": 229,
                  "end": 240,
                  "loc": {
                    "start": {
                      "line": 7,
                      "column": 19
                    },
                    "end": {
                      "line": 7,
                      "column": 30
                    },
                    "identifierName": "_NamedTuple"
                  },
                  "name": "_NamedTuple"
                },
                "arguments": [
                  {
                    "type": "Identifier",
                    "start": 242,
                    "end": 246,
                    "loc": {
                      "start": {
                        "line": 7,
                        "column": 32
                      },
                      "end": {
                        "line": 7,
                        "column": 36
                      },
                      "identifierName": "Dict"
                    },
                    "name": "Dict"
                  },
                  {
                    "type": "Identifier",
                    "start": 249,
                    "end": 260,
                    "loc": {
                      "start": {
                        "line": 7,
                        "column": 39
                      },
                      "end": {
                        "line": 7,
                        "column": 50
                      },
                      "identifierName": "OrderedDict"
                    },
                    "name": "OrderedDict"
                  }
                ]
              }
            }
          ],
          "kind": "const",
          "leadingComments": [],
          "trailingComments": []
        },
        "specifiers": null,
        "source": null,
        "leadingComments": null
      }
    ],
    "directives": []
  },
  "comments": [],
  "tokens": [
    {
      "type": {
        "label": "import",
        "keyword": "import",
        "beforeExpr": false,
        "startsExpr": true,
        "rightAssociative": false,
        "isLoop": false,
        "isAssign": false,
        "prefix": false,
        "postfix": false,
        "binop": null,
        "updateContext": null
      },
      "value": "import",
      "start": 0,
      "end": 6,
      "loc": {
        "start": {
          "line": 1,
          "column": 0
        },
        "end": {
          "line": 1,
          "column": 6
        }
      }
    },
    {
      "type": {
        "label": "name",
        "beforeExpr": false,
        "startsExpr": true,
        "rightAssociative": false,
        "isLoop": false,
        "isAssign": false,
        "prefix": false,
        "postfix": false,
        "binop": null
      },
      "value": "_NamedTuple",
      "start": 7,
      "end": 18,
      "loc": {
        "start": {
          "line": 1,
          "column": 7
        },
        "end": {
          "line": 1,
          "column": 18
        }
      }
    },
    {
      "type": {
        "label": "name",
        "beforeExpr": false,
        "startsExpr": true,
        "rightAssociative": false,
        "isLoop": false,
        "isAssign": false,
        "prefix": false,
        "postfix": false,
        "binop": null
      },
      "value": "from",
      "start": 19,
      "end": 23,
      "loc": {
        "start": {
          "line": 1,
          "column": 19
        },
        "end": {
          "line": 1,
          "column": 23
        }
      }
    },
    {
      "type": {
        "label": "string",
        "beforeExpr": false,
        "startsExpr": true,
        "rightAssociative": false,
        "isLoop": false,
        "isAssign": false,
        "prefix": false,
        "postfix": false,
        "binop": null,
        "updateContext": null
      },
      "value": "./_NamedTuple",
      "start": 24,
      "end": 39,
      "loc": {
        "start": {
          "line": 1,
          "column": 24
        },
        "end": {
          "line": 1,
          "column": 39
        }
      }
    },
    {
      "type": {
        "label": ";",
        "beforeExpr": true,
        "startsExpr": false,
        "rightAssociative": false,
        "isLoop": false,
        "isAssign": false,
        "prefix": false,
        "postfix": false,
        "binop": null,
        "updateContext": null
      },
      "start": 40,
      "end": 41,
      "loc": {
        "start": {
          "line": 1,
          "column": 40
        },
        "end": {
          "line": 1,
          "column": 41
        }
      }
    },
    {
      "type": {
        "label": "import",
        "keyword": "import",
        "beforeExpr": false,
        "startsExpr": true,
        "rightAssociative": false,
        "isLoop": false,
        "isAssign": false,
        "prefix": false,
        "postfix": false,
        "binop": null,
        "updateContext": null
      },
      "value": "import",
      "start": 42,
      "end": 48,
      "loc": {
        "start": {
          "line": 2,
          "column": 0
        },
        "end": {
          "line": 2,
          "column": 6
        }
      }
    },
    {
      "type": {
        "label": "name",
        "beforeExpr": false,
        "startsExpr": true,
        "rightAssociative": false,
        "isLoop": false,
        "isAssign": false,
        "prefix": false,
        "postfix": false,
        "binop": null
      },
      "value": "_namedtuple",
      "start": 49,
      "end": 60,
      "loc": {
        "start": {
          "line": 2,
          "column": 7
        },
        "end": {
          "line": 2,
          "column": 18
        }
      }
    },
    {
      "type": {
        "label": "name",
        "beforeExpr": false,
        "startsExpr": true,
        "rightAssociative": false,
        "isLoop": false,
        "isAssign": false,
        "prefix": false,
        "postfix": false,
        "binop": null
      },
      "value": "from",
      "start": 61,
      "end": 65,
      "loc": {
        "start": {
          "line": 2,
          "column": 19
        },
        "end": {
          "line": 2,
          "column": 23
        }
      }
    },
    {
      "type": {
        "label": "string",
        "beforeExpr": false,
        "startsExpr": true,
        "rightAssociative": false,
        "isLoop": false,
        "isAssign": false,
        "prefix": false,
        "postfix": false,
        "binop": null,
        "updateContext": null
      },
      "value": "./_namedtuple",
      "start": 66,
      "end": 81,
      "loc": {
        "start": {
          "line": 2,
          "column": 24
        },
        "end": {
          "line": 2,
          "column": 39
        }
      }
    },
    {
      "type": {
        "label": ";",
        "beforeExpr": true,
        "startsExpr": false,
        "rightAssociative": false,
        "isLoop": false,
        "isAssign": false,
        "prefix": false,
        "postfix": false,
        "binop": null,
        "updateContext": null
      },
      "start": 82,
      "end": 83,
      "loc": {
        "start": {
          "line": 2,
          "column": 40
        },
        "end": {
          "line": 2,
          "column": 41
        }
      }
    },
    {
      "type": {
        "label": "import",
        "keyword": "import",
        "beforeExpr": false,
        "startsExpr": true,
        "rightAssociative": false,
        "isLoop": false,
        "isAssign": false,
        "prefix": false,
        "postfix": false,
        "binop": null,
        "updateContext": null
      },
      "value": "import",
      "start": 85,
      "end": 91,
      "loc": {
        "start": {
          "line": 4,
          "column": 0
        },
        "end": {
          "line": 4,
          "column": 6
        }
      }
    },
    {
      "type": {
        "label": "{",
        "beforeExpr": true,
        "startsExpr": true,
        "rightAssociative": false,
        "isLoop": false,
        "isAssign": false,
        "prefix": false,
        "postfix": false,
        "binop": null
      },
      "start": 92,
      "end": 93,
      "loc": {
        "start": {
          "line": 4,
          "column": 7
        },
        "end": {
          "line": 4,
          "column": 8
        }
      }
    },
    {
      "type": {
        "label": "name",
        "beforeExpr": false,
        "startsExpr": true,
        "rightAssociative": false,
        "isLoop": false,
        "isAssign": false,
        "prefix": false,
        "postfix": false,
        "binop": null
      },
      "value": "Dict",
      "start": 94,
      "end": 98,
      "loc": {
        "start": {
          "line": 4,
          "column": 9
        },
        "end": {
          "line": 4,
          "column": 13
        }
      }
    },
    {
      "type": {
        "label": "}",
        "beforeExpr": false,
        "startsExpr": false,
        "rightAssociative": false,
        "isLoop": false,
        "isAssign": false,
        "prefix": false,
        "postfix": false,
        "binop": null
      },
      "start": 99,
      "end": 100,
      "loc": {
        "start": {
          "line": 4,
          "column": 14
        },
        "end": {
          "line": 4,
          "column": 15
        }
      }
    },
    {
      "type": {
        "label": "name",
        "beforeExpr": false,
        "startsExpr": true,
        "rightAssociative": false,
        "isLoop": false,
        "isAssign": false,
        "prefix": false,
        "postfix": false,
        "binop": null
      },
      "value": "from",
      "start": 101,
      "end": 105,
      "loc": {
        "start": {
          "line": 4,
          "column": 16
        },
        "end": {
          "line": 4,
          "column": 20
        }
      }
    },
    {
      "type": {
        "label": "string",
        "beforeExpr": false,
        "startsExpr": true,
        "rightAssociative": false,
        "isLoop": false,
        "isAssign": false,
        "prefix": false,
        "postfix": false,
        "binop": null,
        "updateContext": null
      },
      "value": "@aureooms/js-collections-dict",
      "start": 106,
      "end": 137,
      "loc": {
        "start": {
          "line": 4,
          "column": 21
        },
        "end": {
          "line": 4,
          "column": 52
        }
      }
    },
    {
      "type": {
        "label": ";",
        "beforeExpr": true,
        "startsExpr": false,
        "rightAssociative": false,
        "isLoop": false,
        "isAssign": false,
        "prefix": false,
        "postfix": false,
        "binop": null,
        "updateContext": null
      },
      "start": 138,
      "end": 139,
      "loc": {
        "start": {
          "line": 4,
          "column": 53
        },
        "end": {
          "line": 4,
          "column": 54
        }
      }
    },
    {
      "type": {
        "label": "import",
        "keyword": "import",
        "beforeExpr": false,
        "startsExpr": true,
        "rightAssociative": false,
        "isLoop": false,
        "isAssign": false,
        "prefix": false,
        "postfix": false,
        "binop": null,
        "updateContext": null
      },
      "value": "import",
      "start": 140,
      "end": 146,
      "loc": {
        "start": {
          "line": 5,
          "column": 0
        },
        "end": {
          "line": 5,
          "column": 6
        }
      }
    },
    {
      "type": {
        "label": "{",
        "beforeExpr": true,
        "startsExpr": true,
        "rightAssociative": false,
        "isLoop": false,
        "isAssign": false,
        "prefix": false,
        "postfix": false,
        "binop": null
      },
      "start": 147,
      "end": 148,
      "loc": {
        "start": {
          "line": 5,
          "column": 7
        },
        "end": {
          "line": 5,
          "column": 8
        }
      }
    },
    {
      "type": {
        "label": "name",
        "beforeExpr": false,
        "startsExpr": true,
        "rightAssociative": false,
        "isLoop": false,
        "isAssign": false,
        "prefix": false,
        "postfix": false,
        "binop": null
      },
      "value": "OrderedDict",
      "start": 149,
      "end": 160,
      "loc": {
        "start": {
          "line": 5,
          "column": 9
        },
        "end": {
          "line": 5,
          "column": 20
        }
      }
    },
    {
      "type": {
        "label": "}",
        "beforeExpr": false,
        "startsExpr": false,
        "rightAssociative": false,
        "isLoop": false,
        "isAssign": false,
        "prefix": false,
        "postfix": false,
        "binop": null
      },
      "start": 161,
      "end": 162,
      "loc": {
        "start": {
          "line": 5,
          "column": 21
        },
        "end": {
          "line": 5,
          "column": 22
        }
      }
    },
    {
      "type": {
        "label": "name",
        "beforeExpr": false,
        "startsExpr": true,
        "rightAssociative": false,
        "isLoop": false,
        "isAssign": false,
        "prefix": false,
        "postfix": false,
        "binop": null
      },
      "value": "from",
      "start": 163,
      "end": 167,
      "loc": {
        "start": {
          "line": 5,
          "column": 23
        },
        "end": {
          "line": 5,
          "column": 27
        }
      }
    },
    {
      "type": {
        "label": "string",
        "beforeExpr": false,
        "startsExpr": true,
        "rightAssociative": false,
        "isLoop": false,
        "isAssign": false,
        "prefix": false,
        "postfix": false,
        "binop": null,
        "updateContext": null
      },
      "value": "@aureooms/js-collections-ordereddict",
      "start": 168,
      "end": 206,
      "loc": {
        "start": {
          "line": 5,
          "column": 28
        },
        "end": {
          "line": 5,
          "column": 66
        }
      }
    },
    {
      "type": {
        "label": ";",
        "beforeExpr": true,
        "startsExpr": false,
        "rightAssociative": false,
        "isLoop": false,
        "isAssign": false,
        "prefix": false,
        "postfix": false,
        "binop": null,
        "updateContext": null
      },
      "start": 207,
      "end": 208,
      "loc": {
        "start": {
          "line": 5,
          "column": 67
        },
        "end": {
          "line": 5,
          "column": 68
        }
      }
    },
    {
      "type": {
        "label": "const",
        "keyword": "const",
        "beforeExpr": false,
        "startsExpr": false,
        "rightAssociative": false,
        "isLoop": false,
        "isAssign": false,
        "prefix": false,
        "postfix": false,
        "binop": null,
        "updateContext": null
      },
      "value": "const",
      "start": 210,
      "end": 215,
      "loc": {
        "start": {
          "line": 7,
          "column": 0
        },
        "end": {
          "line": 7,
          "column": 5
        }
      }
    },
    {
      "type": {
        "label": "name",
        "beforeExpr": false,
        "startsExpr": true,
        "rightAssociative": false,
        "isLoop": false,
        "isAssign": false,
        "prefix": false,
        "postfix": false,
        "binop": null
      },
      "value": "NamedTuple",
      "start": 216,
      "end": 226,
      "loc": {
        "start": {
          "line": 7,
          "column": 6
        },
        "end": {
          "line": 7,
          "column": 16
        }
      }
    },
    {
      "type": {
        "label": "=",
        "beforeExpr": true,
        "startsExpr": false,
        "rightAssociative": false,
        "isLoop": false,
        "isAssign": true,
        "prefix": false,
        "postfix": false,
        "binop": null,
        "updateContext": null
      },
      "value": "=",
      "start": 227,
      "end": 228,
      "loc": {
        "start": {
          "line": 7,
          "column": 17
        },
        "end": {
          "line": 7,
          "column": 18
        }
      }
    },
    {
      "type": {
        "label": "name",
        "beforeExpr": false,
        "startsExpr": true,
        "rightAssociative": false,
        "isLoop": false,
        "isAssign": false,
        "prefix": false,
        "postfix": false,
        "binop": null
      },
      "value": "_NamedTuple",
      "start": 229,
      "end": 240,
      "loc": {
        "start": {
          "line": 7,
          "column": 19
        },
        "end": {
          "line": 7,
          "column": 30
        }
      }
    },
    {
      "type": {
        "label": "(",
        "beforeExpr": true,
        "startsExpr": true,
        "rightAssociative": false,
        "isLoop": false,
        "isAssign": false,
        "prefix": false,
        "postfix": false,
        "binop": null
      },
      "start": 240,
      "end": 241,
      "loc": {
        "start": {
          "line": 7,
          "column": 30
        },
        "end": {
          "line": 7,
          "column": 31
        }
      }
    },
    {
      "type": {
        "label": "name",
        "beforeExpr": false,
        "startsExpr": true,
        "rightAssociative": false,
        "isLoop": false,
        "isAssign": false,
        "prefix": false,
        "postfix": false,
        "binop": null
      },
      "value": "Dict",
      "start": 242,
      "end": 246,
      "loc": {
        "start": {
          "line": 7,
          "column": 32
        },
        "end": {
          "line": 7,
          "column": 36
        }
      }
    },
    {
      "type": {
        "label": ",",
        "beforeExpr": true,
        "startsExpr": false,
        "rightAssociative": false,
        "isLoop": false,
        "isAssign": false,
        "prefix": false,
        "postfix": false,
        "binop": null,
        "updateContext": null
      },
      "start": 247,
      "end": 248,
      "loc": {
        "start": {
          "line": 7,
          "column": 37
        },
        "end": {
          "line": 7,
          "column": 38
        }
      }
    },
    {
      "type": {
        "label": "name",
        "beforeExpr": false,
        "startsExpr": true,
        "rightAssociative": false,
        "isLoop": false,
        "isAssign": false,
        "prefix": false,
        "postfix": false,
        "binop": null
      },
      "value": "OrderedDict",
      "start": 249,
      "end": 260,
      "loc": {
        "start": {
          "line": 7,
          "column": 39
        },
        "end": {
          "line": 7,
          "column": 50
        }
      }
    },
    {
      "type": {
        "label": ")",
        "beforeExpr": false,
        "startsExpr": false,
        "rightAssociative": false,
        "isLoop": false,
        "isAssign": false,
        "prefix": false,
        "postfix": false,
        "binop": null
      },
      "start": 261,
      "end": 262,
      "loc": {
        "start": {
          "line": 7,
          "column": 51
        },
        "end": {
          "line": 7,
          "column": 52
        }
      }
    },
    {
      "type": {
        "label": ";",
        "beforeExpr": true,
        "startsExpr": false,
        "rightAssociative": false,
        "isLoop": false,
        "isAssign": false,
        "prefix": false,
        "postfix": false,
        "binop": null,
        "updateContext": null
      },
      "start": 263,
      "end": 264,
      "loc": {
        "start": {
          "line": 7,
          "column": 53
        },
        "end": {
          "line": 7,
          "column": 54
        }
      }
    },
    {
      "type": {
        "label": "const",
        "keyword": "const",
        "beforeExpr": false,
        "startsExpr": false,
        "rightAssociative": false,
        "isLoop": false,
        "isAssign": false,
        "prefix": false,
        "postfix": false,
        "binop": null,
        "updateContext": null
      },
      "value": "const",
      "start": 265,
      "end": 270,
      "loc": {
        "start": {
          "line": 8,
          "column": 0
        },
        "end": {
          "line": 8,
          "column": 5
        }
      }
    },
    {
      "type": {
        "label": "name",
        "beforeExpr": false,
        "startsExpr": true,
        "rightAssociative": false,
        "isLoop": false,
        "isAssign": false,
        "prefix": false,
        "postfix": false,
        "binop": null
      },
      "value": "namedtuple",
      "start": 271,
      "end": 281,
      "loc": {
        "start": {
          "line": 8,
          "column": 6
        },
        "end": {
          "line": 8,
          "column": 16
        }
      }
    },
    {
      "type": {
        "label": "=",
        "beforeExpr": true,
        "startsExpr": false,
        "rightAssociative": false,
        "isLoop": false,
        "isAssign": true,
        "prefix": false,
        "postfix": false,
        "binop": null,
        "updateContext": null
      },
      "value": "=",
      "start": 282,
      "end": 283,
      "loc": {
        "start": {
          "line": 8,
          "column": 17
        },
        "end": {
          "line": 8,
          "column": 18
        }
      }
    },
    {
      "type": {
        "label": "name",
        "beforeExpr": false,
        "startsExpr": true,
        "rightAssociative": false,
        "isLoop": false,
        "isAssign": false,
        "prefix": false,
        "postfix": false,
        "binop": null
      },
      "value": "_namedtuple",
      "start": 284,
      "end": 295,
      "loc": {
        "start": {
          "line": 8,
          "column": 19
        },
        "end": {
          "line": 8,
          "column": 30
        }
      }
    },
    {
      "type": {
        "label": "(",
        "beforeExpr": true,
        "startsExpr": true,
        "rightAssociative": false,
        "isLoop": false,
        "isAssign": false,
        "prefix": false,
        "postfix": false,
        "binop": null
      },
      "start": 295,
      "end": 296,
      "loc": {
        "start": {
          "line": 8,
          "column": 30
        },
        "end": {
          "line": 8,
          "column": 31
        }
      }
    },
    {
      "type": {
        "label": "name",
        "beforeExpr": false,
        "startsExpr": true,
        "rightAssociative": false,
        "isLoop": false,
        "isAssign": false,
        "prefix": false,
        "postfix": false,
        "binop": null
      },
      "value": "NamedTuple",
      "start": 297,
      "end": 307,
      "loc": {
        "start": {
          "line": 8,
          "column": 32
        },
        "end": {
          "line": 8,
          "column": 42
        }
      }
    },
    {
      "type": {
        "label": ")",
        "beforeExpr": false,
        "startsExpr": false,
        "rightAssociative": false,
        "isLoop": false,
        "isAssign": false,
        "prefix": false,
        "postfix": false,
        "binop": null
      },
      "start": 308,
      "end": 309,
      "loc": {
        "start": {
          "line": 8,
          "column": 43
        },
        "end": {
          "line": 8,
          "column": 44
        }
      }
    },
    {
      "type": {
        "label": ";",
        "beforeExpr": true,
        "startsExpr": false,
        "rightAssociative": false,
        "isLoop": false,
        "isAssign": false,
        "prefix": false,
        "postfix": false,
        "binop": null,
        "updateContext": null
      },
      "start": 310,
      "end": 311,
      "loc": {
        "start": {
          "line": 8,
          "column": 45
        },
        "end": {
          "line": 8,
          "column": 46
        }
      }
    },
    {
      "type": {
        "label": "export",
        "keyword": "export",
        "beforeExpr": false,
        "startsExpr": false,
        "rightAssociative": false,
        "isLoop": false,
        "isAssign": false,
        "prefix": false,
        "postfix": false,
        "binop": null,
        "updateContext": null
      },
      "value": "export",
      "start": 313,
      "end": 319,
      "loc": {
        "start": {
          "line": 10,
          "column": 0
        },
        "end": {
          "line": 10,
          "column": 6
        }
      }
    },
    {
      "type": {
        "label": "default",
        "keyword": "default",
        "beforeExpr": true,
        "startsExpr": false,
        "rightAssociative": false,
        "isLoop": false,
        "isAssign": false,
        "prefix": false,
        "postfix": false,
        "binop": null,
        "updateContext": null
      },
      "value": "default",
      "start": 320,
      "end": 327,
      "loc": {
        "start": {
          "line": 10,
          "column": 7
        },
        "end": {
          "line": 10,
          "column": 14
        }
      }
    },
    {
      "type": {
        "label": "name",
        "beforeExpr": false,
        "startsExpr": true,
        "rightAssociative": false,
        "isLoop": false,
        "isAssign": false,
        "prefix": false,
        "postfix": false,
        "binop": null
      },
      "value": "namedtuple",
      "start": 328,
      "end": 338,
      "loc": {
        "start": {
          "line": 10,
          "column": 15
        },
        "end": {
          "line": 10,
          "column": 25
        }
      }
    },
    {
      "type": {
        "label": ";",
        "beforeExpr": true,
        "startsExpr": false,
        "rightAssociative": false,
        "isLoop": false,
        "isAssign": false,
        "prefix": false,
        "postfix": false,
        "binop": null,
        "updateContext": null
      },
      "start": 339,
      "end": 340,
      "loc": {
        "start": {
          "line": 10,
          "column": 26
        },
        "end": {
          "line": 10,
          "column": 27
        }
      }
    },
    {
      "type": {
        "label": "export",
        "keyword": "export",
        "beforeExpr": false,
        "startsExpr": false,
        "rightAssociative": false,
        "isLoop": false,
        "isAssign": false,
        "prefix": false,
        "postfix": false,
        "binop": null,
        "updateContext": null
      },
      "value": "export",
      "start": 342,
      "end": 348,
      "loc": {
        "start": {
          "line": 12,
          "column": 0
        },
        "end": {
          "line": 12,
          "column": 6
        }
      }
    },
    {
      "type": {
        "label": "{",
        "beforeExpr": true,
        "startsExpr": true,
        "rightAssociative": false,
        "isLoop": false,
        "isAssign": false,
        "prefix": false,
        "postfix": false,
        "binop": null
      },
      "start": 349,
      "end": 350,
      "loc": {
        "start": {
          "line": 12,
          "column": 7
        },
        "end": {
          "line": 12,
          "column": 8
        }
      }
    },
    {
      "type": {
        "label": "name",
        "beforeExpr": false,
        "startsExpr": true,
        "rightAssociative": false,
        "isLoop": false,
        "isAssign": false,
        "prefix": false,
        "postfix": false,
        "binop": null
      },
      "value": "namedtuple",
      "start": 352,
      "end": 362,
      "loc": {
        "start": {
          "line": 13,
          "column": 1
        },
        "end": {
          "line": 13,
          "column": 11
        }
      }
    },
    {
      "type": {
        "label": ",",
        "beforeExpr": true,
        "startsExpr": false,
        "rightAssociative": false,
        "isLoop": false,
        "isAssign": false,
        "prefix": false,
        "postfix": false,
        "binop": null,
        "updateContext": null
      },
      "start": 363,
      "end": 364,
      "loc": {
        "start": {
          "line": 13,
          "column": 12
        },
        "end": {
          "line": 13,
          "column": 13
        }
      }
    },
    {
      "type": {
        "label": "name",
        "beforeExpr": false,
        "startsExpr": true,
        "rightAssociative": false,
        "isLoop": false,
        "isAssign": false,
        "prefix": false,
        "postfix": false,
        "binop": null
      },
      "value": "NamedTuple",
      "start": 366,
      "end": 376,
      "loc": {
        "start": {
          "line": 14,
          "column": 1
        },
        "end": {
          "line": 14,
          "column": 11
        }
      }
    },
    {
      "type": {
        "label": ",",
        "beforeExpr": true,
        "startsExpr": false,
        "rightAssociative": false,
        "isLoop": false,
        "isAssign": false,
        "prefix": false,
        "postfix": false,
        "binop": null,
        "updateContext": null
      },
      "start": 377,
      "end": 378,
      "loc": {
        "start": {
          "line": 14,
          "column": 12
        },
        "end": {
          "line": 14,
          "column": 13
        }
      }
    },
    {
      "type": {
        "label": "name",
        "beforeExpr": false,
        "startsExpr": true,
        "rightAssociative": false,
        "isLoop": false,
        "isAssign": false,
        "prefix": false,
        "postfix": false,
        "binop": null
      },
      "value": "_namedtuple",
      "start": 380,
      "end": 391,
      "loc": {
        "start": {
          "line": 15,
          "column": 1
        },
        "end": {
          "line": 15,
          "column": 12
        }
      }
    },
    {
      "type": {
        "label": ",",
        "beforeExpr": true,
        "startsExpr": false,
        "rightAssociative": false,
        "isLoop": false,
        "isAssign": false,
        "prefix": false,
        "postfix": false,
        "binop": null,
        "updateContext": null
      },
      "start": 392,
      "end": 393,
      "loc": {
        "start": {
          "line": 15,
          "column": 13
        },
        "end": {
          "line": 15,
          "column": 14
        }
      }
    },
    {
      "type": {
        "label": "name",
        "beforeExpr": false,
        "startsExpr": true,
        "rightAssociative": false,
        "isLoop": false,
        "isAssign": false,
        "prefix": false,
        "postfix": false,
        "binop": null
      },
      "value": "_NamedTuple",
      "start": 395,
      "end": 406,
      "loc": {
        "start": {
          "line": 16,
          "column": 1
        },
        "end": {
          "line": 16,
          "column": 12
        }
      }
    },
    {
      "type": {
        "label": ",",
        "beforeExpr": true,
        "startsExpr": false,
        "rightAssociative": false,
        "isLoop": false,
        "isAssign": false,
        "prefix": false,
        "postfix": false,
        "binop": null,
        "updateContext": null
      },
      "start": 407,
      "end": 408,
      "loc": {
        "start": {
          "line": 16,
          "column": 13
        },
        "end": {
          "line": 16,
          "column": 14
        }
      }
    },
    {
      "type": {
        "label": "}",
        "beforeExpr": false,
        "startsExpr": false,
        "rightAssociative": false,
        "isLoop": false,
        "isAssign": false,
        "prefix": false,
        "postfix": false,
        "binop": null
      },
      "start": 409,
      "end": 410,
      "loc": {
        "start": {
          "line": 17,
          "column": 0
        },
        "end": {
          "line": 17,
          "column": 1
        }
      }
    },
    {
      "type": {
        "label": ";",
        "beforeExpr": true,
        "startsExpr": false,
        "rightAssociative": false,
        "isLoop": false,
        "isAssign": false,
        "prefix": false,
        "postfix": false,
        "binop": null,
        "updateContext": null
      },
      "start": 411,
      "end": 412,
      "loc": {
        "start": {
          "line": 17,
          "column": 2
        },
        "end": {
          "line": 17,
          "column": 3
        }
      }
    },
    {
      "type": {
        "label": "eof",
        "beforeExpr": false,
        "startsExpr": false,
        "rightAssociative": false,
        "isLoop": false,
        "isAssign": false,
        "prefix": false,
        "postfix": false,
        "binop": null,
        "updateContext": null
      },
      "start": 413,
      "end": 413,
      "loc": {
        "start": {
          "line": 18,
          "column": 0
        },
        "end": {
          "line": 18,
          "column": 0
        }
      }
    }
  ]
}